scikit_ext
