Metadata-Version: 1.2
Name: scikit-ext
Version: 0.1.15
Summary: Various scikit-learn extensions
Home-page: https://github.com/denver1117/scikit-ext
Author: Evan Harris
Author-email: emitchellh@gmail.com
License: MIT
Download-URL: https://pypi.org/project/scikit-ext/#files
Platform: UNKNOWN
Classifier: Development Status :: 4 - Beta
Classifier: Intended Audience :: Developers
Classifier: License :: OSI Approved :: MIT License
Classifier: Programming Language :: Python
Classifier: Topic :: Scientific/Engineering :: Artificial Intelligence
Requires-Python: >=3.5
